{
  "node": {
    "00079c28e89cb4e91bdd03590ed50ac388823ade0c": {
      "workers": {
        "app/(admin-panel)/admin/about/page": {
          "moduleId": 84818,
          "async": false,
          "exportedName": "getAboutContent",
          "filename": "Official/SbWebsite/client/app/actions/about.ts"
        }
      },
      "layer": {
        "app/(admin-panel)/admin/about/page": "action-browser"
      },
      "exportedName": "getAboutContent",
      "filename": "Official/SbWebsite/client/app/actions/about.ts"
    },
    "40219cd4be3543d79675f9788b312971d2d56c6311": {
      "workers": {
        "app/(admin-panel)/admin/about/page": {
          "moduleId": 84818,
          "async": false,
          "exportedName": "updateAboutContent",
          "filename": "Official/SbWebsite/client/app/actions/about.ts"
        }
      },
      "layer": {
        "app/(admin-panel)/admin/about/page": "action-browser"
      },
      "exportedName": "updateAboutContent",
      "filename": "Official/SbWebsite/client/app/actions/about.ts"
    }
  },
  "edge": {}
}